corek/__init__.py
corek/corek_grammar.lark
corek/rules_engine.py
corek/transformer/__init__.py
corek/transformer/corek_transformer.py
corek-0.0.2.dist-info/LICENCE
corek-0.0.2.dist-info/METADATA
corek-0.0.2.dist-info/WHEEL
corek-0.0.2.dist-info/top_level.txt
corek-0.0.2.dist-info/RECORD
