Metadata-Version: 2.1
Name: corek
Version: 0.0.2
Summary: One line expression evaluator
Author: Rai Raman
Project-URL: Homepage, https://github.com/rairaman/corek
Classifier: License :: OSI Approved :: MIT License
Classifier: Natural Language :: English
Classifier: Operating System :: OS Independent
Classifier: Programming Language :: Python
Requires-Python: >=3.9
License-File: LICENCE
Requires-Dist: lark ~=1.1.8
Requires-Dist: importlib-resources ==6.1.1
